myproject/__init__.py
myproject/main.py
myprojectxyz-0.0.1.dist-info/LICENSE
myprojectxyz-0.0.1.dist-info/METADATA
myprojectxyz-0.0.1.dist-info/WHEEL
myprojectxyz-0.0.1.dist-info/top_level.txt
myprojectxyz-0.0.1.dist-info/RECORD
