Metadata-Version: 2.1
Name: myprojectxyz
Version: 0.0.1
Summary: My fabulous new project
Home-page: http://bla.blubb.de
Author: Matthias Baer
Author-email: matthias.r.baer@googlemail.com
License: MIT
Platform: ALL
Classifier: Operating System :: OS Independent
Classifier: Programming Language :: Python :: 3
Requires-Python: >=3.6
Requires-Dist: sphinx
